oooenv/__init__.py
oooenv/cli/__init__.py
oooenv/cli/main.py
oooenv/cmds/__init__.py
oooenv/cmds/install.py
oooenv/cmds/manage_env_cfg.py
oooenv/cmds/uno_lnk.py
oooenv/cmds/updater.py
oooenv/utils/__init__.py
oooenv/utils/local_paths.py
oooenv/utils/sys_info.py
oooenv/utils/uno_paths.py
oooenv-0.2.4.dist-info/LICENSE
oooenv-0.2.4.dist-info/METADATA
oooenv-0.2.4.dist-info/WHEEL
oooenv-0.2.4.dist-info/entry_points.txt
oooenv-0.2.4.dist-info/RECORD
