Metadata-Version: 2.1
Name: oooenv
Version: 0.2.4
Summary: Configures a project python environment for LibreOffice UNO.
Home-page: https://github.com/Amourspirit/python_oooenv
License: MIT
Keywords: libreoffice,macro,uno,ooouno,venv
Author: :Barry-Thomas-Paul: Moss
Author-email: vibrationoflife@protonmail.com
Requires-Python: >=3.8,<4.0
Classifier: Intended Audience :: Developers
Classifier: License :: OSI Approved :: Apache Software License
Classifier: License :: OSI Approved :: MIT License
Classifier: Operating System :: OS Independent
Classifier: Programming Language :: Python
Classifier: Programming Language :: Python :: 3
Classifier: Programming Language :: Python :: 3.8
Classifier: Programming Language :: Python :: 3.9
Classifier: Programming Language :: Python :: 3.10
Classifier: Programming Language :: Python :: 3.11
Classifier: Programming Language :: Python :: 3.12
Classifier: Topic :: Office/Business
Project-URL: Documentation, https://github.com/Amourspirit/python_oooenv
Project-URL: Repository, https://github.com/Amourspirit/python_oooenv
